{
  "meta":{
    "requests":5290,
    "timestamp":1420353791,
    "status":200,
    "message":"Request successful",
    "method_id":1223,
    "method":{
      
    }
  },
  "data":[
    {
      "class_number":8123,
      "subject":"ARBUS",
      "catalog_number":"200",
      "title":"Entrepreneurship Principles and Practices",
      "section":"LEC 001",
      "weekdays":"Th",
      "start_time":"14:30",
      "end_time":"17:20",
      "start_date":null,
      "end_date":null,
      "enrollment_total":87,
      "instructors":[
        "Malleck,Geoff"
      ],
      "building":"AL",
      "room":"208",
      "term":1151,
      "last_updated":"2014-12-15T06:09:32-05:00"
    },
    {
      "class_number":8124,
      "subject":"ARBUS",
      "catalog_number":"200",
      "title":"Entrepreneurship Principles and Practices",
      "section":"PRA 101",
      "weekdays":"Th",
      "start_time":"17:30",
      "end_time":"18:20",
      "start_date":null,
      "end_date":null,
      "enrollment_total":87,
      "instructors":[
        "Malleck,Geoff"
      ],
      "building":"AL",
      "room":"208",
      "term":1151,
      "last_updated":"2014-12-15T06:09:32-05:00"
    },
    {
      "class_number":3837,
      "subject":"ARBUS",
      "catalog_number":"302",
      "title":"Marketing: Principles of Marketing and Consumer Economics",
      "section":"LEC 004",
      "weekdays":"TF",
      "start_time":"13:00",
      "end_time":"14:20",
      "start_date":null,
      "end_date":null,
      "enrollment_total":22,
      "instructors":[
        "Mesta,Olivia"
      ],
      "building":"AL",
      "room":"208",
      "term":1151,
      "last_updated":"2014-12-15T06:09:32-05:00"
    },
    {
      "class_number":3504,
      "subject":"ARTS",
      "catalog_number":"111",
      "title":"Career Development and Decision-Making",
      "section":"LEC 001",
      "weekdays":"MW",
      "start_time":"16:00",
      "end_time":"17:20",
      "start_date":null,
      "end_date":null,
      "enrollment_total":85,
      "instructors":[
        "Hayden,Jayne"
      ],
      "building":"AL",
      "room":"208",
      "term":1151,
      "last_updated":"2014-12-15T06:09:35-05:00"
    },
    {
      "class_number":3322,
      "subject":"ECON",
      "catalog_number":"304",
      "title":"Monetary Economics",
      "section":"LEC 001",
      "weekdays":"MW",
      "start_time":"08:30",
      "end_time":"09:50",
      "start_date":null,
      "end_date":null,
      "enrollment_total":100,
      "instructors":[
        "Lam,Jean-Paul"
      ],
      "building":"AL",
      "room":"208",
      "term":1151,
      "last_updated":"2014-12-15T06:11:35-05:00"
    },
    {
      "class_number":3323,
      "subject":"ECON",
      "catalog_number":"321",
      "title":"Introduction to Econometrics",
      "section":"LEC 001",
      "weekdays":"TTh",
      "start_time":"10:00",
      "end_time":"11:20",
      "start_date":null,
      "end_date":null,
      "enrollment_total":51,
      "instructors":[
        "Pierard,Emmanuelle"
      ],
      "building":"AL",
      "room":"208",
      "term":1151,
      "last_updated":"2014-12-15T06:11:35-05:00"
    },
    {
      "class_number":3324,
      "subject":"ECON",
      "catalog_number":"332",
      "title":"International Finance",
      "section":"LEC 001",
      "weekdays":"TF",
      "start_time":"16:00",
      "end_time":"17:20",
      "start_date":null,
      "end_date":null,
      "enrollment_total":54,
      "instructors":[
        "He,Zhen"
      ],
      "building":"AL",
      "room":"208",
      "term":1151,
      "last_updated":"2014-12-15T06:11:36-05:00"
    },
    {
      "class_number":3836,
      "subject":"ECON",
      "catalog_number":"344",
      "title":"Marketing: Principles of Marketing and Consumer Economics",
      "section":"LEC 004",
      "weekdays":"TF",
      "start_time":"13:00",
      "end_time":"14:20",
      "start_date":null,
      "end_date":null,
      "enrollment_total":31,
      "instructors":[
        "Mesta,Olivia"
      ],
      "building":"AL",
      "room":"208",
      "term":1151,
      "last_updated":"2014-12-15T06:11:36-05:00"
    },
    {
      "class_number":4128,
      "subject":"GBDA",
      "catalog_number":"204",
      "title":"Applied Leadership and Management",
      "section":"LEC 001",
      "weekdays":"Th",
      "start_time":"11:30",
      "end_time":"14:20",
      "start_date":null,
      "end_date":null,
      "enrollment_total":41,
      "instructors":[
        "Siebel-Achenbach,Sebastian"
      ],
      "building":"AL",
      "room":"208",
      "term":1151,
      "last_updated":"2014-12-15T06:12:14-05:00"
    },
    {
      "class_number":8070,
      "subject":"HIST",
      "catalog_number":"266",
      "title":"The British Empire 1857-1956",
      "section":"LEC 001",
      "weekdays":"TF",
      "start_time":"08:30",
      "end_time":"09:20",
      "start_date":null,
      "end_date":null,
      "enrollment_total":26,
      "instructors":[
        "Gorman,Daniel P"
      ],
      "building":"AL",
      "room":"208",
      "term":1151,
      "last_updated":"2014-12-15T06:12:34-05:00"
    },
    {
      "class_number":7009,
      "subject":"PHYS",
      "catalog_number":"111",
      "title":"Physics 1",
      "section":"TUT 103",
      "weekdays":"F",
      "start_time":"09:30",
      "end_time":"10:20",
      "start_date":null,
      "end_date":null,
      "enrollment_total":103,
      "instructors":[
        "Bohlouli Zanjani,Parisa"
      ],
      "building":"AL",
      "room":"208",
      "term":1151,
      "last_updated":"2014-12-15T06:14:03-05:00"
    },
    {
      "class_number":7905,
      "subject":"PSCI",
      "catalog_number":"250",
      "title":"The Comparative Politics of State and Nation",
      "section":"LEC 001",
      "weekdays":"MW",
      "start_time":"10:00",
      "end_time":"11:20",
      "start_date":null,
      "end_date":null,
      "enrollment_total":54,
      "instructors":[
        "Jaworsky,John S"
      ],
      "building":"AL",
      "room":"208",
      "term":1151,
      "last_updated":"2014-12-15T06:14:21-05:00"
    },
    {
      "class_number":3614,
      "subject":"ECON",
      "catalog_number":"651",
      "title":"Labour Economics",
      "section":"LEC 001",
      "weekdays":"MW",
      "start_time":"11:30",
      "end_time":"12:50",
      "start_date":null,
      "end_date":null,
      "enrollment_total":4,
      "instructors":[
        "Ferrer,Ana"
      ],
      "building":"AL",
      "room":"208",
      "term":1151,
      "last_updated":"2014-12-15T06:16:17-05:00"
    },
    {
      "class_number":7410,
      "subject":"ME",
      "catalog_number":"725",
      "title":"Special Topics in Advanced Stress Analysis",
      "section":"LEC 001",
      "weekdays":"M",
      "start_time":"13:00",
      "end_time":"15:50",
      "start_date":null,
      "end_date":null,
      "enrollment_total":3,
      "instructors":[
        "Worswick,Michael J"
      ],
      "building":"AL",
      "room":"208",
      "term":1151,
      "last_updated":"2014-12-15T06:16:47-05:00"
    }
  ]
}