{
  "meta":{
    "requests":5384,
    "timestamp":1420353825,
    "status":200,
    "message":"Request successful",
    "method_id":1223,
    "method":{
      
    }
  },
  "data":[
    {
      "class_number":5122,
      "subject":"CIVE",
      "catalog_number":"381",
      "title":"Hydraulics",
      "section":"LAB 201",
      "weekdays":"M",
      "start_time":"08:30",
      "end_time":"09:20",
      "start_date":null,
      "end_date":null,
      "enrollment_total":19,
      "instructors":[
        
      ],
      "building":"E3",
      "room":"2103",
      "term":1151,
      "last_updated":"2014-12-15T06:10:37-05:00"
    },
    {
      "class_number":5298,
      "subject":"CIVE",
      "catalog_number":"381",
      "title":"Hydraulics",
      "section":"LAB 202",
      "weekdays":"W",
      "start_time":"08:30",
      "end_time":"09:20",
      "start_date":null,
      "end_date":null,
      "enrollment_total":15,
      "instructors":[
        
      ],
      "building":"E3",
      "room":"2103",
      "term":1151,
      "last_updated":"2014-12-15T06:10:37-05:00"
    },
    {
      "class_number":5299,
      "subject":"CIVE",
      "catalog_number":"381",
      "title":"Hydraulics",
      "section":"LAB 203",
      "weekdays":"F",
      "start_time":"08:30",
      "end_time":"09:20",
      "start_date":null,
      "end_date":null,
      "enrollment_total":12,
      "instructors":[
        
      ],
      "building":"E3",
      "room":"2103",
      "term":1151,
      "last_updated":"2014-12-15T06:10:37-05:00"
    },
    {
      "class_number":5105,
      "subject":"MTE",
      "catalog_number":"262",
      "title":"Introduction to Microprocessors and Digital Logic",
      "section":"LAB 101",
      "weekdays":"T",
      "start_time":"14:30",
      "end_time":"17:20",
      "start_date":null,
      "end_date":null,
      "enrollment_total":37,
      "instructors":[
        
      ],
      "building":"E3",
      "room":"2103",
      "term":1151,
      "last_updated":"2014-12-15T06:13:26-05:00"
    },
    {
      "class_number":5106,
      "subject":"MTE",
      "catalog_number":"262",
      "title":"Introduction to Microprocessors and Digital Logic",
      "section":"LAB 102",
      "weekdays":"W",
      "start_time":"14:30",
      "end_time":"17:20",
      "start_date":null,
      "end_date":null,
      "enrollment_total":36,
      "instructors":[
        
      ],
      "building":"E3",
      "room":"2103",
      "term":1151,
      "last_updated":"2014-12-15T06:13:26-05:00"
    },
    {
      "class_number":5107,
      "subject":"MTE",
      "catalog_number":"262",
      "title":"Introduction to Microprocessors and Digital Logic",
      "section":"LAB 103",
      "weekdays":"Th",
      "start_time":"14:30",
      "end_time":"17:20",
      "start_date":null,
      "end_date":null,
      "enrollment_total":36,
      "instructors":[
        
      ],
      "building":"E3",
      "room":"2103",
      "term":1151,
      "last_updated":"2014-12-15T06:13:26-05:00"
    },
    {
      "class_number":5108,
      "subject":"MTE",
      "catalog_number":"262",
      "title":"Introduction to Microprocessors and Digital Logic",
      "section":"LAB 104",
      "weekdays":"F",
      "start_time":"14:30",
      "end_time":"17:20",
      "start_date":null,
      "end_date":null,
      "enrollment_total":28,
      "instructors":[
        
      ],
      "building":"E3",
      "room":"2103",
      "term":1151,
      "last_updated":"2014-12-15T06:13:26-05:00"
    }
  ]
}