{
  "meta":{
    "requests":5428,
    "timestamp":1420353841,
    "status":200,
    "message":"Request successful",
    "method_id":1223,
    "method":{
      
    }
  },
  "data":[
    {
      "class_number":8004,
      "subject":"PLAN",
      "catalog_number":"416",
      "title":"Modelling the City",
      "section":"LAB 101",
      "weekdays":"F",
      "start_time":"12:30",
      "end_time":"13:20",
      "start_date":null,
      "end_date":null,
      "enrollment_total":13,
      "instructors":[
        "Parker,Dawn Cassandra"
      ],
      "building":"EV2",
      "room":"1014",
      "term":1151,
      "last_updated":"2014-12-15T06:14:14-05:00"
    },
    {
      "class_number":8005,
      "subject":"PLAN",
      "catalog_number":"416",
      "title":"Modelling the City",
      "section":"LAB 102",
      "weekdays":"F",
      "start_time":"11:30",
      "end_time":"12:20",
      "start_date":null,
      "end_date":null,
      "enrollment_total":9,
      "instructors":[
        "Parker,Dawn Cassandra"
      ],
      "building":"EV2",
      "room":"1014",
      "term":1151,
      "last_updated":"2014-12-15T06:14:14-05:00"
    },
    {
      "class_number":8013,
      "subject":"PLAN",
      "catalog_number":"674",
      "title":"Special Topics in Planning",
      "section":"LAB 101",
      "weekdays":"F",
      "start_time":"12:30",
      "end_time":"13:20",
      "start_date":null,
      "end_date":null,
      "enrollment_total":1,
      "instructors":[
        "Parker,Dawn Cassandra"
      ],
      "building":"EV2",
      "room":"1014",
      "term":1151,
      "last_updated":"2014-12-15T06:17:03-05:00"
    },
    {
      "class_number":8014,
      "subject":"PLAN",
      "catalog_number":"674",
      "title":"Special Topics in Planning",
      "section":"LAB 102",
      "weekdays":"F",
      "start_time":"11:30",
      "end_time":"12:20",
      "start_date":null,
      "end_date":null,
      "enrollment_total":3,
      "instructors":[
        "Parker,Dawn Cassandra"
      ],
      "building":"EV2",
      "room":"1014",
      "term":1151,
      "last_updated":"2014-12-15T06:17:03-05:00"
    }
  ]
}