{
  "meta":{
    "requests":5491,
    "timestamp":1420353862,
    "status":200,
    "message":"Request successful",
    "method_id":1223,
    "method":{
      
    }
  },
  "data":[
    {
      "class_number":6229,
      "subject":"ACTSC",
      "catalog_number":"455",
      "title":"Advanced Life Insurance Practice",
      "section":"LEC 001",
      "weekdays":"MTTh",
      "start_time":"12:30",
      "end_time":"13:20",
      "start_date":null,
      "end_date":null,
      "enrollment_total":19,
      "instructors":[
        "Skrzydlo,Diana Katherine"
      ],
      "building":"MC",
      "room":"4063",
      "term":1151,
      "last_updated":"2014-12-15T06:09:16-05:00"
    },
    {
      "class_number":5738,
      "subject":"AMATH",
      "catalog_number":"353",
      "title":"Partial Differential Equations 1",
      "section":"LEC 001",
      "weekdays":"MWF",
      "start_time":"10:30",
      "end_time":"11:20",
      "start_date":null,
      "end_date":null,
      "enrollment_total":42,
      "instructors":[
        "Chang,Dong Eui"
      ],
      "building":"MC",
      "room":"4063",
      "term":1151,
      "last_updated":"2014-12-15T06:09:24-05:00"
    },
    {
      "class_number":5743,
      "subject":"AMATH",
      "catalog_number":"475",
      "title":"Introduction to General Relativity",
      "section":"LEC 001",
      "weekdays":"MWF",
      "start_time":"08:30",
      "end_time":"09:20",
      "start_date":null,
      "end_date":null,
      "enrollment_total":19,
      "instructors":[
        "Hewitt,Conrad G"
      ],
      "building":"MC",
      "room":"4063",
      "term":1151,
      "last_updated":"2014-12-15T06:09:26-05:00"
    },
    {
      "class_number":6262,
      "subject":"CO",
      "catalog_number":"255",
      "title":"Introduction to Optimization (Advanced Level)",
      "section":"LEC 001",
      "weekdays":"MW",
      "start_time":"16:00",
      "end_time":"17:20",
      "start_date":null,
      "end_date":null,
      "enrollment_total":25,
      "instructors":[
        "Vavasis,Stephen"
      ],
      "building":"MC",
      "room":"4063",
      "term":1151,
      "last_updated":"2014-12-15T06:10:44-05:00"
    },
    {
      "class_number":7724,
      "subject":"CS",
      "catalog_number":"136",
      "title":"Elementary Algorithm Design and Data Abstraction",
      "section":"TUT 111",
      "weekdays":"W",
      "start_time":"09:30",
      "end_time":"10:20",
      "start_date":null,
      "end_date":null,
      "enrollment_total":55,
      "instructors":[
        
      ],
      "building":"MC",
      "room":"4063",
      "term":1151,
      "last_updated":"2014-12-15T06:10:52-05:00"
    },
    {
      "class_number":6196,
      "subject":"CS",
      "catalog_number":"241",
      "title":"Foundations of Sequential Programs",
      "section":"TUT 104",
      "weekdays":"F",
      "start_time":"09:30",
      "end_time":"10:20",
      "start_date":null,
      "end_date":null,
      "enrollment_total":61,
      "instructors":[
        
      ],
      "building":"MC",
      "room":"4063",
      "term":1151,
      "last_updated":"2014-12-15T06:10:53-05:00"
    },
    {
      "class_number":6197,
      "subject":"CS",
      "catalog_number":"245",
      "title":"Logic and Computation",
      "section":"TUT 102",
      "weekdays":"F",
      "start_time":"13:30",
      "end_time":"14:20",
      "start_date":null,
      "end_date":null,
      "enrollment_total":55,
      "instructors":[
        
      ],
      "building":"MC",
      "room":"4063",
      "term":1151,
      "last_updated":"2014-12-15T06:10:54-05:00"
    },
    {
      "class_number":5791,
      "subject":"CS",
      "catalog_number":"492",
      "title":"The Social Implications of Computing",
      "section":"LEC 001",
      "weekdays":"MWF",
      "start_time":"14:30",
      "end_time":"15:20",
      "start_date":null,
      "end_date":null,
      "enrollment_total":45,
      "instructors":[
        "Trefler,Richard"
      ],
      "building":"MC",
      "room":"4063",
      "term":1151,
      "last_updated":"2014-12-15T06:11:04-05:00"
    },
    {
      "class_number":4938,
      "subject":"ECE",
      "catalog_number":"103",
      "title":"Discrete Mathematics",
      "section":"TUT 101",
      "weekdays":"T",
      "start_time":"08:30",
      "end_time":"10:20",
      "start_date":null,
      "end_date":null,
      "enrollment_total":55,
      "instructors":[
        "Pei,Martin"
      ],
      "building":"MC",
      "room":"4063",
      "term":1151,
      "last_updated":"2014-12-15T06:11:21-05:00"
    },
    {
      "class_number":4943,
      "subject":"ECE",
      "catalog_number":"106",
      "title":"Physics of Electrical Engineering 2",
      "section":"TUT 101",
      "weekdays":"Th",
      "start_time":"08:30",
      "end_time":"10:20",
      "start_date":null,
      "end_date":null,
      "enrollment_total":50,
      "instructors":[
        "Mansour,Firas K"
      ],
      "building":"MC",
      "room":"4063",
      "term":1151,
      "last_updated":"2014-12-15T06:11:21-05:00"
    },
    {
      "class_number":5030,
      "subject":"ECE",
      "catalog_number":"106",
      "title":"Physics of Electrical Engineering 2",
      "section":"TUT 106",
      "weekdays":"Th",
      "start_time":"13:30",
      "end_time":"15:20",
      "start_date":null,
      "end_date":null,
      "enrollment_total":46,
      "instructors":[
        "Saini,Simarjeet S."
      ],
      "building":"MC",
      "room":"4063",
      "term":1151,
      "last_updated":"2014-12-15T06:11:21-05:00"
    },
    {
      "class_number":5806,
      "subject":"MATH",
      "catalog_number":"119",
      "title":"Calculus 2 for Engineering",
      "section":"TUT 102",
      "weekdays":"Th",
      "start_time":"15:30",
      "end_time":"17:20",
      "start_date":null,
      "end_date":null,
      "enrollment_total":52,
      "instructors":[
        "Miskovic,Zoran"
      ],
      "building":"MC",
      "room":"4063",
      "term":1151,
      "last_updated":"2014-12-15T06:13:09-05:00"
    },
    {
      "class_number":5908,
      "subject":"MATH",
      "catalog_number":"119",
      "title":"Calculus 2 for Engineering",
      "section":"TUT 104",
      "weekdays":"T",
      "start_time":"13:30",
      "end_time":"15:20",
      "start_date":null,
      "end_date":null,
      "enrollment_total":46,
      "instructors":[
        "Garbary,Robert"
      ],
      "building":"MC",
      "room":"4063",
      "term":1151,
      "last_updated":"2014-12-15T06:13:09-05:00"
    },
    {
      "class_number":4641,
      "subject":"ME",
      "catalog_number":"322",
      "title":"Mechanical Design 1",
      "section":"TUT 201",
      "weekdays":"M",
      "start_time":"13:30",
      "end_time":"14:20",
      "start_date":null,
      "end_date":null,
      "enrollment_total":41,
      "instructors":[
        
      ],
      "building":"MC",
      "room":"4063",
      "term":1151,
      "last_updated":"2014-12-15T06:13:14-05:00"
    },
    {
      "class_number":6684,
      "subject":"PHYS",
      "catalog_number":"476",
      "title":"Introduction to General Relativity",
      "section":"LEC 001",
      "weekdays":"MWF",
      "start_time":"08:30",
      "end_time":"09:20",
      "start_date":null,
      "end_date":null,
      "enrollment_total":27,
      "instructors":[
        "Hewitt,Conrad G"
      ],
      "building":"MC",
      "room":"4063",
      "term":1151,
      "last_updated":"2014-12-15T06:14:12-05:00"
    },
    {
      "class_number":5436,
      "subject":"PLAN",
      "catalog_number":"233",
      "title":"People and Plans",
      "section":"TUT 103",
      "weekdays":"Th",
      "start_time":"10:30",
      "end_time":"11:20",
      "start_date":null,
      "end_date":null,
      "enrollment_total":30,
      "instructors":[
        
      ],
      "building":"MC",
      "room":"4063",
      "term":1151,
      "last_updated":"2014-12-15T06:14:13-05:00"
    },
    {
      "class_number":5437,
      "subject":"PLAN",
      "catalog_number":"233",
      "title":"People and Plans",
      "section":"TUT 104",
      "weekdays":"Th",
      "start_time":"11:30",
      "end_time":"12:20",
      "start_date":null,
      "end_date":null,
      "enrollment_total":26,
      "instructors":[
        
      ],
      "building":"MC",
      "room":"4063",
      "term":1151,
      "last_updated":"2014-12-15T06:14:13-05:00"
    },
    {
      "class_number":5756,
      "subject":"STAT",
      "catalog_number":"440",
      "title":"Computational Inference",
      "section":"LEC 001",
      "weekdays":"TF",
      "start_time":"16:00",
      "end_time":"17:20",
      "start_date":null,
      "end_date":null,
      "enrollment_total":30,
      "instructors":[
        "Chenouri,Shojaeddin"
      ],
      "building":"MC",
      "room":"4063",
      "term":1151,
      "last_updated":"2014-12-15T06:15:17-05:00"
    },
    {
      "class_number":6230,
      "subject":"ACTSC",
      "catalog_number":"855",
      "title":"Advanced Life Insurance Practice",
      "section":"LEC 001",
      "weekdays":"MTTh",
      "start_time":"12:30",
      "end_time":"13:20",
      "start_date":null,
      "end_date":null,
      "enrollment_total":3,
      "instructors":[
        "Skrzydlo,Diana Katherine"
      ],
      "building":"MC",
      "room":"4063",
      "term":1151,
      "last_updated":"2014-12-15T06:15:40-05:00"
    },
    {
      "class_number":5703,
      "subject":"AMATH",
      "catalog_number":"675",
      "title":"General Relativity",
      "section":"LEC 001",
      "weekdays":"MWF",
      "start_time":"08:30",
      "end_time":"09:20",
      "start_date":null,
      "end_date":null,
      "enrollment_total":0,
      "instructors":[
        "Hewitt,Conrad G"
      ],
      "building":"MC",
      "room":"4063",
      "term":1151,
      "last_updated":"2014-12-15T06:15:41-05:00"
    },
    {
      "class_number":6097,
      "subject":"CM",
      "catalog_number":"761",
      "title":"Computational Inference",
      "section":"LEC 001",
      "weekdays":"TF",
      "start_time":"16:00",
      "end_time":"17:20",
      "start_date":null,
      "end_date":null,
      "enrollment_total":1,
      "instructors":[
        "Chenouri,Shojaeddin"
      ],
      "building":"MC",
      "room":"4063",
      "term":1151,
      "last_updated":"2014-12-15T06:15:56-05:00"
    },
    {
      "class_number":5714,
      "subject":"CS",
      "catalog_number":"692",
      "title":"The Social Implications of Computing",
      "section":"LEC 001",
      "weekdays":"MWF",
      "start_time":"14:30",
      "end_time":"15:20",
      "start_date":null,
      "end_date":null,
      "enrollment_total":0,
      "instructors":[
        "Trefler,Richard"
      ],
      "building":"MC",
      "room":"4063",
      "term":1151,
      "last_updated":"2014-12-15T06:16:05-05:00"
    },
    {
      "class_number":5717,
      "subject":"STAT",
      "catalog_number":"840",
      "title":"Computational Inference",
      "section":"LEC 001",
      "weekdays":"TF",
      "start_time":"16:00",
      "end_time":"17:20",
      "start_date":null,
      "end_date":null,
      "enrollment_total":10,
      "instructors":[
        "Chenouri,Shojaeddin"
      ],
      "building":"MC",
      "room":"4063",
      "term":1151,
      "last_updated":"2014-12-15T06:17:17-05:00"
    }
  ]
}